luna/__init__.py
luna/client.py
luna/auth/__init__.py
luna/auth/api_key.py
luna/auth/storage.py
luna/auth/token.py
luna/auth/types.py
luna/config/__init__.py
luna/errors/__init__.py
luna/errors/base.py
luna/errors/codes.py
luna/http/__init__.py
luna/http/client.py
luna/http/types.py
luna/resources/__init__.py
luna/resources/ai.py
luna/resources/automation.py
luna/resources/identity.py
luna/resources/pagination.py
luna/resources/projects.py
luna/resources/resmate.py
luna/resources/storage.py
luna/resources/users.py
luna/telemetry/__init__.py
luna/telemetry/logger.py
luna/telemetry/types.py
luna/types/__init__.py
luna/utils/__init__.py
luna/utils/system.py
luna_sdk-1.0.1.dist-info/METADATA
luna_sdk-1.0.1.dist-info/WHEEL
luna_sdk-1.0.1.dist-info/RECORD
