Metadata-Version: 2.4
Name: luna-sdk
Version: 1.0.1
Summary: Official Python SDK for the Eclipse Softworks Platform API
Project-URL: Homepage, https://github.com/eclipse-softworks/luna-sdk
Project-URL: Documentation, https://docs.eclipse.dev/luna/python
Project-URL: Repository, https://github.com/eclipse-softworks/luna-sdk.git
Project-URL: Changelog, https://github.com/eclipse-softworks/luna-sdk/blob/main/CHANGELOG.md
Author-email: Eclipse Softworks <sdk@eclipse.dev>
License: MIT
Keywords: api,async,client,eclipse,luna,sdk
Classifier: Development Status :: 4 - Beta
Classifier: Framework :: AsyncIO
Classifier: Intended Audience :: Developers
Classifier: License :: OSI Approved :: MIT License
Classifier: Operating System :: OS Independent
Classifier: Programming Language :: Python :: 3
Classifier: Programming Language :: Python :: 3.9
Classifier: Programming Language :: Python :: 3.10
Classifier: Programming Language :: Python :: 3.11
Classifier: Programming Language :: Python :: 3.12
Classifier: Typing :: Typed
Requires-Python: >=3.9
Requires-Dist: httpx>=0.25.0
Requires-Dist: keyring>=24.0.0
Requires-Dist: pydantic>=2.0.0
Provides-Extra: dev
Requires-Dist: mypy>=1.7.0; extra == 'dev'
Requires-Dist: pre-commit>=3.6.0; extra == 'dev'
Requires-Dist: pytest-asyncio>=0.21.0; extra == 'dev'
Requires-Dist: pytest-cov>=4.1.0; extra == 'dev'
Requires-Dist: pytest-mock>=3.12.0; extra == 'dev'
Requires-Dist: pytest>=7.4.0; extra == 'dev'
Requires-Dist: ruff>=0.1.6; extra == 'dev'
Provides-Extra: docs
Requires-Dist: mkdocs-material>=9.5.0; extra == 'docs'
Requires-Dist: mkdocs>=1.5.0; extra == 'docs'
Requires-Dist: mkdocstrings[python]>=0.24.0; extra == 'docs'
Provides-Extra: telemetry
Requires-Dist: opentelemetry-api>=1.20.0; extra == 'telemetry'
Requires-Dist: opentelemetry-sdk>=1.20.0; extra == 'telemetry'
